README.md
setup.py
plane_kitasddsa.egg-info/PKG-INFO
plane_kitasddsa.egg-info/SOURCES.txt
plane_kitasddsa.egg-info/dependency_links.txt
plane_kitasddsa.egg-info/requires.txt
plane_kitasddsa.egg-info/top_level.txt
planekit/Calculator.py
planekit/__init__.py
planekit/command/DoReposition.py
planekit/command/FightMode.py
planekit/command/SetArm.py
planekit/command/TakeOffLandCMD.py
planekit/command/__init__.py
planekit/data/Ahrs.py
planekit/data/Attributes.py
planekit/data/Gps.py
planekit/data/Heartbeat.py
planekit/data/HudMetrics.py
planekit/data/Imu.py
planekit/data/__init__.py
planekit/exception/ConnectionIsNoneError.py
planekit/exception/Error.py
planekit/exception/__init__.py
planekit/mavlink/Connection.py
planekit/mavlink/ReceiveData.py
planekit/mavlink/SendMessage.py
planekit/mavlink/__init__.py